allocine
